droppii/__init__.py
droppii/__main__.py
droppii/_cli.py
droppii/_replace_bytes_values.py
droppii/censor.py
droppii/replace_df_fields.py
droppii/s3_get.py
droppii-1.0.0.dist-info/LICENSE.md
droppii-1.0.0.dist-info/METADATA
droppii-1.0.0.dist-info/WHEEL
droppii-1.0.0.dist-info/top_level.txt
droppii-1.0.0.dist-info/RECORD
