Metadata-Version: 2.1
Name: droppii
Version: 1.0.0
Summary: General purpose tool to process data from S3 and anonymize fields containing personally identifiable information.
Classifier: Programming Language :: Python :: 3
Classifier: License :: OSI Approved :: Apache Software License
Classifier: Operating System :: Unix
Requires-Python: >=3.11
License-File: LICENSE.md
Requires-Dist: boto3
Requires-Dist: polars
Provides-Extra: dev
Requires-Dist: autopep8 ; extra == 'dev'
Requires-Dist: bandit ; extra == 'dev'
Requires-Dist: flake8 ; extra == 'dev'
Requires-Dist: mkdocs ; extra == 'dev'
Requires-Dist: moto ; extra == 'dev'
Requires-Dist: safety ; extra == 'dev'
Requires-Dist: pytest ; extra == 'dev'
Requires-Dist: pytest-cov ; extra == 'dev'
Requires-Dist: Faker ; extra == 'dev'
